mahotas-1.4.18.dist-info/RECORD
mahotas-1.4.18.dist-info/AUTHORS
mahotas-1.4.18.dist-info/WHEEL
mahotas-1.4.18.dist-info/entry_points.txt
mahotas-1.4.18.dist-info/COPYING
mahotas-1.4.18.dist-info/top_level.txt
mahotas-1.4.18.dist-info/METADATA
mahotas/internal.py
mahotas/bwperim.py
mahotas/features_cli.py
mahotas/_bbox.cpython-312-darwin.so
mahotas/mahotas_version.py
mahotas/edge.py
mahotas/stretch.py
mahotas/zernike.py
mahotas/histogram.py
mahotas/_distance.cpython-312-darwin.so
mahotas/convolve.py
mahotas/freeimage.py
mahotas/moments.py
mahotas/_convex.cpython-312-darwin.so
mahotas/polygon.py
mahotas/_labeled.cpython-312-darwin.so
mahotas/__init__.py
mahotas/thresholding.py
mahotas/morph.py
mahotas/tas.py
mahotas/thin.py
mahotas/distance.py
mahotas/resize.py
mahotas/_interpolate.cpython-312-darwin.so
mahotas/lbp.py
mahotas/texture.py
mahotas/_morph.cpython-312-darwin.so
mahotas/interpolate.py
mahotas/_center_of_mass.cpython-312-darwin.so
mahotas/_histogram.cpython-312-darwin.so
mahotas/_filters.py
mahotas/center_of_mass.py
mahotas/_convolve.cpython-312-darwin.so
mahotas/bbox.py
mahotas/surf.py
mahotas/labeled.py
mahotas/segmentation.py
mahotas/_thin.cpython-312-darwin.so
mahotas/euler.py
mahotas/colors.py
mahotas/io/freeimage.py
mahotas/io/__init__.py
mahotas/io/pil.py
mahotas/features/_texture.cpython-312-darwin.so
mahotas/features/zernike.py
mahotas/features/moments.py
mahotas/features/__init__.py
mahotas/features/tas.py
mahotas/features/_zernike.cpython-312-darwin.so
mahotas/features/_lbp.cpython-312-darwin.so
mahotas/features/lbp.py
mahotas/features/texture.py
mahotas/features/shape.py
mahotas/features/_surf.cpython-312-darwin.so
mahotas/features/surf.py
mahotas/tests/test_stretch.py
mahotas/tests/test_zernike.py
mahotas/tests/test_gvoronoi.py
mahotas/tests/test_convolve.py
mahotas/tests/test_hitmiss.py
mahotas/tests/test_edge.py
mahotas/tests/test_label.py
mahotas/tests/test_segmentation.py
mahotas/tests/test_mahotas.py
mahotas/tests/test_imresize.py
mahotas/tests/test_center_of_mass.py
mahotas/tests/test_distance.py
mahotas/tests/test_bwperim.py
mahotas/tests/test_tas.py
mahotas/tests/test_watershed.py
