Metadata-Version: 2.1
Name: mahotas
Version: 1.4.18
Summary: Mahotas: Computer Vision Library
Home-page: https://luispedro.org/software/mahotas
Author: Luis Pedro Coelho
Author-email: luis@luispedro.org
License: MIT
Platform: Any
Classifier: Development Status :: 5 - Production/Stable
Classifier: Intended Audience :: Developers
Classifier: Intended Audience :: Science/Research
Classifier: Topic :: Scientific/Engineering :: Image Recognition
Classifier: Topic :: Software Development :: Libraries
Classifier: Programming Language :: Python
Classifier: Programming Language :: Python :: 2
Classifier: Programming Language :: Python :: 2.7
Classifier: Programming Language :: Python :: 3
Classifier: Programming Language :: Python :: 3.3
Classifier: Programming Language :: Python :: 3.4
Classifier: Programming Language :: Python :: 3.5
Classifier: Programming Language :: Python :: 3.6
Classifier: Programming Language :: Python :: 3.7
Classifier: Programming Language :: Python :: 3.8
Classifier: Programming Language :: Python :: 3.9
Classifier: Programming Language :: Python :: 3.10
Classifier: Programming Language :: Python :: 3.11
Classifier: Programming Language :: Python :: 3.12
Classifier: Programming Language :: C++
Classifier: Operating System :: OS Independent
Classifier: License :: OSI Approved :: MIT License
License-File: COPYING
License-File: AUTHORS
Requires-Dist: numpy
Provides-Extra: tests
Requires-Dist: matplotlib ; extra == 'tests'
Requires-Dist: pip ; extra == 'tests'
Requires-Dist: coveralls ; extra == 'tests'
Requires-Dist: pytest <=8.1.1 ; extra == 'tests'
Requires-Dist: scipy ; extra == 'tests'
Requires-Dist: pillow ; extra == 'tests'
